Metadata-Version: 2.0
Name: sicksid-drf-tus
Version: 1.22.0
Summary: A Tus (tus.io) library for Django Rest Framework (copied for now from
Home-page: https://github.com/sicksid/drf-tus.git
Author: Dirk Moors
Author-email: dirkmoors@gmail.com
License: MIT
Keywords: drf-tus,tus,django,rest,framework,django-rest-framework
Classifier: Development Status :: 5 - Production/Stable
Classifier: Framework :: Django
Classifier: Framework :: Django :: 3.0
Classifier: Framework :: Django :: 4.0
Classifier: Intended Audience :: Developers
Classifier: License :: OSI Approved :: MIT License
Classifier: Natural Language :: English
Classifier: Programming Language :: Python :: 3.4
Classifier: Programming Language :: Python :: 3.5
Classifier: Programming Language :: Python :: 3.6
Classifier: Programming Language :: Python :: 3.7
Classifier: Programming Language :: Python :: 3.8
Classifier: Programming Language :: Python :: 3.9
Classifier: Programming Language :: Python :: 3.10
Classifier: Programming Language :: Python :: 3.11
Classifier: Topic :: Software Development :: Libraries :: Python Modules
License-File: LICENSE
License-File: AUTHORS.rst
Requires-Dist: Django (<=4.1,>=1.8)
Requires-Dist: djangorestframework (>=3.5.4)
Requires-Dist: jsonfield (>=2.0.0)
Requires-Dist: django-fsm (==2.8.0)
Requires-Dist: six (>=1.11.0)
